snet/__init__.py
snet/cli/__init__.py
snet/cli/arguments.py
snet/cli/config.py
snet/cli/contract.py
snet/cli/identity.py
snet/cli/commands/__init__.py
snet/cli/commands/commands.py
snet/cli/commands/mpe_account.py
snet/cli/commands/mpe_channel.py
snet/cli/commands/mpe_client.py
snet/cli/commands/mpe_service.py
snet/cli/commands/mpe_treasurer.py
snet/cli/commands/sdk_command.py
snet/cli/metadata/__init__.py
snet/cli/metadata/organization.py
snet/cli/metadata/service.py
snet/cli/resources/org_schema.json
snet/cli/resources/root_certificate.py
snet/cli/resources/service_schema.json
snet/cli/resources/proto/control_service.proto
snet/cli/resources/proto/control_service_pb2.py
snet/cli/resources/proto/control_service_pb2_grpc.py
snet/cli/resources/proto/state_service.proto
snet/cli/resources/proto/state_service_pb2.py
snet/cli/resources/proto/state_service_pb2_grpc.py
snet/cli/resources/proto/token_service.proto
snet/cli/resources/proto/token_service_pb2.py
snet/cli/resources/proto/token_service_pb2_grpc.py
snet/cli/resources/proto/training.proto
snet/cli/resources/proto/training_pb2.py
snet/cli/resources/proto/training_pb2_grpc.py
snet/cli/resources/proto/training/training.proto
snet/cli/test/functional_tests/func_tests.py
snet/cli/test/functional_tests/test_aapreparation.py
snet/cli/test/functional_tests/test_channels.py
snet/cli/test/functional_tests/test_client.py
snet/cli/test/functional_tests/test_commands.py
snet/cli/test/functional_tests/test_contract.py
snet/cli/test/functional_tests/test_deposit_withdraw_transfer.py
snet/cli/test/functional_tests/test_encryption_key.py
snet/cli/test/functional_tests/test_entry_point.py
snet/cli/test/functional_tests/test_generate_library.py
snet/cli/test/functional_tests/test_onboarding.py
snet/cli/test/functional_tests/test_org_metadata.py
snet/cli/test/functional_tests/test_unset.py
snet/cli/test/functional_tests/simple_daemon/test_simple_daemon.py
snet/cli/test/unit_tests/test_mpe_service_metadata_1.py
snet_cli-3.1.0.dist-info/licenses/LICENSE
snet_cli-3.1.0.dist-info/METADATA
snet_cli-3.1.0.dist-info/WHEEL
snet_cli-3.1.0.dist-info/entry_points.txt
snet_cli-3.1.0.dist-info/top_level.txt
snet_cli-3.1.0.dist-info/RECORD
