Metadata-Version: 2.4
Name: snet-cli
Version: 3.1.0
Summary: SingularityNET CLI
Author-email: SingularityNET Foundation <info@singularitynet.io>
License: MIT
Project-URL: Homepage, https://github.com/singnet/snet-cli
Requires-Python: >=3.10
License-File: LICENSE
Requires-Dist: protobuf~=6.30
Requires-Dist: grpcio~=1.59
Requires-Dist: grpcio-tools~=1.59
Requires-Dist: wheel~=0.45
Requires-Dist: rlp~=4.0
Requires-Dist: web3~=7.0
Requires-Dist: mnemonic==0.21
Requires-Dist: pyyaml~=6.0.1
Requires-Dist: ipfshttpclient==0.4.13.2
Requires-Dist: pymultihash==0.8.2
Requires-Dist: base58==2.1.1
Requires-Dist: argcomplete~=3.1
Requires-Dist: grpcio-health-checking~=1.59
Requires-Dist: jsonschema~=4.1
Requires-Dist: eth-account~=0.9
Requires-Dist: trezor~=0.13.8
Requires-Dist: ledgerblue~=0.1.48
Requires-Dist: snet-contracts==1.0.1
Requires-Dist: lighthouseweb3~=0.1.4
Requires-Dist: cryptography~=46.0
Dynamic: license-file
